{
  "gitSyncId": "676e2c1104b16518b088fe23_28db69ad-12ec-42ca-bfd0-c5221a380a74",
  "id": "Authen_GetDivisions",
  "pluginId": "postgres-plugin",
  "pluginType": "DB",
  "unpublishedAction": {
    "actionConfiguration": {
      "body": "SELECT division_id as value, name as label\nFROM division\nORDER BY division_id;\n",
      "encodeParamsToggle": true,
      "paginationType": "NONE",
      "pluginSpecifiedTemplates": [
        {
          "value": true
        }
      ],
      "timeoutInMillisecond": 10000
    },
    "confirmBeforeExecute": false,
    "datasource": {
      "id": "mainDB",
      "isAutoGenerated": false,
      "name": "mainDB",
      "pluginId": "postgres-plugin"
    },
    "dynamicBindingPathList": [],
    "name": "GetDivisions",
    "pageId": "Authen",
    "runBehaviour": "MANUAL",
    "userSetOnLoad": false
  }
}