{
  "gitSyncId": "686e46c8f052af62894e37fb_865b785d-c10e-434d-8556-672a79111bfc",
  "id": "Settings_R_UserType",
  "pluginId": "postgres-plugin",
  "pluginType": "DB",
  "unpublishedAction": {
    "actionConfiguration": {
      "body": "SELECT * FROM public.\"user_type\";",
      "encodeParamsToggle": true,
      "paginationType": "NONE",
      "pluginSpecifiedTemplates": [
        {
          "value": true
        }
      ],
      "timeoutInMillisecond": 10000
    },
    "confirmBeforeExecute": false,
    "datasource": {
      "id": "mainDB",
      "isAutoGenerated": false,
      "name": "mainDB",
      "pluginId": "postgres-plugin"
    },
    "dynamicBindingPathList": [],
    "name": "R_UserType",
    "pageId": "Settings",
    "runBehaviour": "ON_PAGE_LOAD",
    "userSetOnLoad": false
  }
}