{
  "gitSyncId": "676e2c1104b16518b088fe23_82a4198d-0fec-4cdc-b035-6889ccd1032e",
  "id": "Settings_GetUser",
  "pluginId": "postgres-plugin",
  "pluginType": "DB",
  "unpublishedAction": {
    "actionConfiguration": {
      "body": "SELECT u.user_id, u.name, u.email, u.username, u.password, u.division_id, u.user_type_id, u.password_hash, u.salt, u.is_first_login, u.is_temp_password,\n       d.name as division_name, ut.name as type_name\nFROM \"user\" u\nLEFT JOIN division d ON u.division_id = d.division_id\nLEFT JOIN user_type ut ON u.user_type_id = ut.user_type_id",
      "encodeParamsToggle": true,
      "paginationType": "NONE",
      "pluginSpecifiedTemplates": [
        {
          "value": true
        }
      ],
      "timeoutInMillisecond": 10000
    },
    "confirmBeforeExecute": false,
    "datasource": {
      "id": "mainDB",
      "isAutoGenerated": false,
      "name": "mainDB",
      "pluginId": "postgres-plugin"
    },
    "dynamicBindingPathList": [],
    "name": "GetUser",
    "pageId": "Settings",
    "runBehaviour": "MANUAL",
    "userSetOnLoad": false
  }
}