{
  "gitSyncId": "676e2c1104b16518b088fe23_66fea3fa-b7de-4f6d-a222-bc95f108bc3b",
  "id": "Home Page_JSObject2.getNextMonthAndYear",
  "pluginId": "js-plugin",
  "pluginType": "JS",
  "unpublishedAction": {
    "actionConfiguration": {
      "encodeParamsToggle": true,
      "jsArguments": [],
      "paginationType": "NONE",
      "timeoutInMillisecond": 10000
    },
    "collectionId": "Home Page_JSObject2",
    "confirmBeforeExecute": false,
    "datasource": {
      "isAutoGenerated": false,
      "name": "UNUSED_DATASOURCE",
      "pluginId": "js-plugin"
    },
    "dynamicBindingPathList": [
      {
        "key": "body"
      }
    ],
    "fullyQualifiedName": "JSObject2.getNextMonthAndYear",
    "name": "getNextMonthAndYear",
    "pageId": "Home Page",
    "runBehaviour": "MANUAL",
    "userSetOnLoad": false
  }
}