{
  "gitSyncId": "676e2c1104b16518b088fe23_3090ac28-1798-417b-92ce-54c71f764725",
  "id": "Home Page_C_1_Merit",
  "pluginId": "postgres-plugin",
  "pluginType": "DB",
  "unpublishedAction": {
    "actionConfiguration": {
      "body": "SELECT COUNT(*) AS cases_result_3\nFROM \"case\"\nWHERE inves_result = 4;\n",
      "encodeParamsToggle": true,
      "paginationType": "NONE",
      "pluginSpecifiedTemplates": [
        {
          "value": true
        }
      ],
      "timeoutInMillisecond": 10000
    },
    "confirmBeforeExecute": false,
    "datasource": {
      "id": "mainDB",
      "isAutoGenerated": false,
      "name": "mainDB",
      "pluginId": "postgres-plugin"
    },
    "dynamicBindingPathList": [],
    "name": "C_1_Merit",
    "pageId": "Home Page",
    "runBehaviour": "ON_PAGE_LOAD",
    "userSetOnLoad": false
  }
}