{
  "gitSyncId": "676e2c1104b16518b088fe23_eb00a5a3-5822-463a-bd91-931c1986d2ec",
  "id": "Home Page_R_USER_DIVISION",
  "pluginId": "postgres-plugin",
  "pluginType": "DB",
  "unpublishedAction": {
    "actionConfiguration": {
      "body": "SELECT * FROM public.\"division\" WHERE {{appsmith.store.division_id}} = division_id ;",
      "encodeParamsToggle": true,
      "paginationType": "NONE",
      "pluginSpecifiedTemplates": [
        {
          "value": true
        }
      ],
      "timeoutInMillisecond": 10000
    },
    "confirmBeforeExecute": false,
    "datasource": {
      "id": "mainDB",
      "isAutoGenerated": false,
      "name": "mainDB",
      "pluginId": "postgres-plugin"
    },
    "dynamicBindingPathList": [
      {
        "key": "body"
      }
    ],
    "name": "R_USER_DIVISION",
    "pageId": "Home Page",
    "runBehaviour": "ON_PAGE_LOAD",
    "userSetOnLoad": true
  }
}